setup.py
dicks/__init__.py
dicks/client.py
dicks/error.py
python_dicks.egg-info/PKG-INFO
python_dicks.egg-info/SOURCES.txt
python_dicks.egg-info/dependency_links.txt
python_dicks.egg-info/requires.txt
python_dicks.egg-info/top_level.txt
python_dicks.egg-info/zip-safe