Metadata-Version: 1.0
Name: python-dicks
Version: 1.0.0
Summary: A Python client for the Dicks API
Home-page: http://github.com/toashd/python-dicks
Author: Tobias Schmid
Author-email: toashd@gmail.com
License: MIT
Keywords: dicks,dicks as a service
Platform: UNKNOWN
